<?xml version="1.0" encoding="utf-8"?><toc><breadcrumbs><li><a href="626ba618-1967-40a2-8daa-03096aa0d5c8.htm">Docs</a></li></breadcrumbs><tocItems><li><a id="626ba618-1967-40a2-8daa-03096aa0d5c8" href="626ba618-1967-40a2-8daa-03096aa0d5c8.htm">Welcome to the [TODO: Add project name]</a></li><li><a id="11513bd0-89fa-4991-a343-090a8c37fa38" class="has-submenu" href="11513bd0-89fa-4991-a343-090a8c37fa38.htm"><span data-tocFile="../toc/IDB.xml" class="icon toggle" onclick="ToggleExpandCollapse(this); return false;"><i class="fa fa-angle-right"> </i></span>Version History</a><ul class="toc-menu is-hidden"> </ul></li><li><a id="765415da-1375-6eb0-e30f-2d5c2979d134" class="has-submenu" href="765415da-1375-6eb0-e30f-2d5c2979d134.htm"><span data-tocFile="../toc/IDC.xml" class="icon toggle" onclick="ToggleExpandCollapse(this); return false;"><i class="fa fa-angle-right"> </i></span>Car<wbr />To<wbr />Go.<wbr />Areas.<wbr />Identity.<wbr />Pages</a><ul class="toc-menu is-hidden"> </ul></li><li><a id="58a5939e-925d-47f7-26be-763759abba2f" class="has-submenu" href="58a5939e-925d-47f7-26be-763759abba2f.htm"><span data-tocFile="../toc/IDD.xml" class="icon toggle" onclick="ToggleExpandCollapse(this); return false;"><i class="fa fa-angle-right"> </i></span>Car<wbr />To<wbr />Go.<wbr />Areas.<wbr />Identity.<wbr />Pages.<wbr />Account</a><ul class="toc-menu is-hidden"> </ul></li><li><a id="b25c4081-3095-be74-9d4c-fb3632660471" class="has-submenu" href="b25c4081-3095-be74-9d4c-fb3632660471.htm"><span data-tocFile="../toc/IDE.xml" class="icon toggle" onclick="ToggleExpandCollapse(this); return false;"><i class="fa fa-angle-right"> </i></span>Car<wbr />To<wbr />Go.<wbr />Areas.<wbr />Identity.<wbr />Pages.<wbr />Account.<wbr />Manage</a><ul class="toc-menu is-hidden"> </ul></li><li><a id="3a24b51c-bcfc-b4e8-013e-5b30b72dab1e" class="has-submenu" href="3a24b51c-bcfc-b4e8-013e-5b30b72dab1e.htm"><span data-tocFile="../toc/IDF.xml" class="icon toggle" onclick="ToggleExpandCollapse(this); return false;"><i class="fa fa-angle-right"> </i></span>Car<wbr />To<wbr />Go.<wbr />Controllers</a><ul class="toc-menu is-hidden"> </ul></li><li><a id="752dfe5f-ff0e-f99a-ef2c-b2e17b166e9f" class="has-submenu" href="752dfe5f-ff0e-f99a-ef2c-b2e17b166e9f.htm"><span data-tocFile="../toc/IDG.xml" class="icon toggle" onclick="ToggleExpandCollapse(this); return false;"><i class="fa fa-angle-right"> </i></span>Car<wbr />To<wbr />Go.<wbr />Data</a><ul class="toc-menu is-hidden"> </ul></li><li><a id="12b1b727-56e8-7467-64fa-443d746bb10a" class="has-submenu" href="12b1b727-56e8-7467-64fa-443d746bb10a.htm"><span data-tocFile="../toc/IDH.xml" class="icon toggle" onclick="ToggleExpandCollapse(this); return false;"><i class="fa fa-angle-right"> </i></span>Car<wbr />To<wbr />Go.<wbr />Migrations</a><ul class="toc-menu is-hidden"> </ul></li><li><a id="1eda2d90-d9fa-ae6c-1ba2-77eac9eefcd4" class="has-submenu" href="1eda2d90-d9fa-ae6c-1ba2-77eac9eefcd4.htm"><span data-tocFile="../toc/IDI.xml" class="icon toggle" onclick="ToggleExpandCollapse(this); return false;"><i class="fa fa-angle-right"> </i></span>Car<wbr />To<wbr />Go.<wbr />Models</a><ul class="toc-menu is-hidden"> </ul></li><li><a id="1187ae22-1431-5cd9-feae-ba5b56a76899" class="has-submenu" href="1187ae22-1431-5cd9-feae-ba5b56a76899.htm"><span data-tocFile="../toc/IDJ.xml" class="icon toggle" onclick="ToggleExpandCollapse(this); return false;"><i class="fa fa-angle-right"> </i></span>Car<wbr />To<wbr />Go.<wbr />View<wbr />Model</a><ul class="toc-menu is-hidden"> </ul></li><li><a id="a228f9df-3589-9146-3009-e215afb2c862" class="has-submenu" href="a228f9df-3589-9146-3009-e215afb2c862.htm"><span data-tocFile="../toc/IDK.xml" class="icon toggle" onclick="ToggleExpandCollapse(this); return false;"><i class="fa fa-angle-right"> </i></span>Data.<wbr />Migrations</a><ul class="toc-menu is-hidden"> </ul></li></tocItems></toc>